Metadata-Version: 2.1
Name: lixlib
Version: 0.2
Summary: Easy time in lixlib library
Author: AhmedTools
Classifier: Programming Language :: Python :: 3
Classifier: Operating System :: OS Independent
Classifier: License :: OSI Approved :: MIT License
License-File: LICENSE.txt
